MANIFEST.in
README.rst
buildout.cfg
develop.cfg
requirements.txt
setup.py
version.txt
bob/__init__.py
bob.db.replay.egg-info/PKG-INFO
bob.db.replay.egg-info/SOURCES.txt
bob.db.replay.egg-info/dependency_links.txt
bob.db.replay.egg-info/entry_points.txt
bob.db.replay.egg-info/not-zip-safe
bob.db.replay.egg-info/requires.txt
bob.db.replay.egg-info/top_level.txt
bob/db/__init__.py
bob/db/replay/__init__.py
bob/db/replay/checkfiles.py
bob/db/replay/create.py
bob/db/replay/driver.py
bob/db/replay/dumplist.py
bob/db/replay/models.py
bob/db/replay/query.py
bob/db/replay/test.py
doc/conf.py
doc/guide.rst
doc/index.rst
doc/py_api.rst