Metadata-Version: 1.1
Name: bob.db.replay
Version: 3.0.4
Summary: Replay Attack Database Access API for Bob
Home-page: http://gitlab.idiap.ch/bob/bob.db.replay
Author: Andre Anjos, Ivana Chingovska
Author-email: andre.anjos@idiap.ch, ivana.chingovska@idiap.ch
License: BSD
Platform: UNKNOWN
Classifier: Framework :: Bob
Classifier: Development Status :: 4 - Beta
Classifier: Intended Audience :: Science/Research
Classifier: License :: OSI Approved :: BSD License
Classifier: Natural Language :: English
Classifier: Programming Language :: Python
Classifier: Programming Language :: Python :: 3
Classifier: Topic :: Scientific/Engineering :: Artificial Intelligence
Classifier: Topic :: Database :: Front-Ends
